{
  "comprehensiveSeoAudit": {
    "auditDate": "2026-06-14",
    "auditType": "comprehensive",
    "overallScore": 7.8,
    "overallGrade": "B+",
    "status": "GOOD",
    "project": "Mangulina - Dominican Music Database",
    "siteUrl": "https://mangulina.vercel.app",
    "summary": {
      "totalPublicRoutes": 28,
      "routesWithCompleteMetadata": 27,
      "routesWithMissingMetadata": 1,
      "criticalIssues": 1,
      "majorIssues": 4,
      "minorIssues": 5,
      "bestPracticesImplemented": 12,
      "bestPracticesPossible": 15,
      "bestPracticesPercentage": 80
    },
    "assessment": {
      "overallStatus": "Well-structured SEO foundation with room for optimization",
      "strengths": [
        "Solid technical SEO implementation with proper metadata",
        "Canonical URLs on all pages",
        "Dynamic sitemap generation with prioritization",
        "Proper robots.txt with conditional rules",
        "Consistent H1 hierarchy",
        "OpenGraph metadata on 96% of pages",
        "Twitter cards configured",
        "Title templates with brand suffix",
        "Semantic HTML structure",
        "Proper language tag configuration",
        "noindex handling for 404s",
        "Proper metadataBase in root layout"
      ],
      "opportunities": [
        "Add OpenGraph images to 13 category pages",
        "Implement comprehensive structured data (schema.org)",
        "Add breadcrumb navigation",
        "Create FAQ sections with schema",
        "Optimize keyword usage in titles/descriptions",
        "Add alt text to images systematically",
        "Standardize description length",
        "Add Organization and LocalBusiness schema",
        "Implement Person schema on artist pages",
        "Verify new pages are in sitemap"
      ]
    },
    "criticalIssues": [
      {
        "id": "MISSING_SEARCH_METADATA",
        "title": "Missing Metadata on /search",
        "severity": "critical",
        "affected": ["/search"],
        "description": "Search page has no metadata export, falls back to root layout defaults",
        "impact": "HIGH - Users sharing search results get poor meta tags",
        "estimatedTrafficLoss": "0.5-1.0%",
        "estimatedFixTime": "5 minutes",
        "fixPriority": 1,
        "recommendation": "Add createPageMetadata() export with appropriate title and description",
        "implementationComplexity": "trivial"
      }
    ],
    "majorIssues": [
      {
        "id": "MISSING_OG_IMAGES",
        "title": "Missing OpenGraph Images on 13 Category Pages",
        "severity": "major",
        "affectedCount": 13,
        "affected": [
          "/composers", "/songwriters", "/lyricists", "/musicians", "/djs", "/producers",
          "/artists/emerging", "/artists/legends", "/artists/most-awarded",
          "/instrumental-classical", "/discover", "/genres/[slug]", "/provinces/[slug]"
        ],
        "impact": "MEDIUM - Lower CTR on social media (estimated -15-25% without images)",
        "estimatedTrafficLoss": "5-10%",
        "estimatedFixTime": "8 hours",
        "fixPriority": 2,
        "recommendation": "Create OG image templates and update routes with image parameter",
        "socialMediaImpact": "Facebook, Twitter, LinkedIn sharing appears with text only instead of visual cards",
        "implementationComplexity": "moderate"
      },
      {
        "id": "NEW_PAGES_SITEMAP_VERIFICATION",
        "title": "New Pages May Not Be in Sitemap",
        "severity": "major",
        "affectedCount": 5,
        "affected": [
          "/artists/emerging", "/artists/legends", "/artists/most-awarded",
          "/discover", "/instrumental-classical"
        ],
        "impact": "MEDIUM - Slower indexing, may not be discovered by crawlers",
        "estimatedTrafficLoss": "2-3%",
        "estimatedFixTime": "10 minutes",
        "fixPriority": 1,
        "recommendation": "Verify/add to sitemap.ts with appropriate priority values",
        "implementationComplexity": "trivial"
      },
      {
        "id": "PLACEHOLDER_MANIFEST",
        "title": "Placeholder Manifest.json",
        "severity": "major",
        "affectedFile": "src/app/manifest.json",
        "impact": "LOW-MEDIUM - PWA shows wrong name, brand consistency issue",
        "estimatedFixTime": "2 minutes",
        "fixPriority": 1,
        "recommendation": "Update manifest.json with proper site name and short name",
        "implementationComplexity": "trivial"
      },
      {
        "id": "LIMITED_STRUCTURED_DATA",
        "title": "Limited Structured Data Implementation",
        "severity": "major",
        "currentCoverage": "3 pages",
        "potentialCoverage": "28 pages",
        "coveragePercentage": 10.7,
        "impact": "MEDIUM - Missing rich snippets, knowledge graph presence, voice search optimization",
        "estimatedTrafficGain": "5-15%",
        "estimatedFixTime": "8 hours",
        "fixPriority": 2,
        "missingSchemas": [
          "Organization (homepage)",
          "LocalBusiness (Dominican context)",
          "Person (artist pages)",
          "MusicAlbum (release pages)",
          "AudioObject (song pages)",
          "FAQPage (about, contact pages)"
        ],
        "recommendation": "Implement comprehensive schema.org structured data library functions",
        "implementationComplexity": "moderate"
      }
    ],
    "minorIssues": [
      {
        "id": "KEYWORD_OPTIMIZATION",
        "title": "Keyword Optimization in Descriptions",
        "severity": "minor",
        "affectedPercentage": "30%",
        "impact": "LOW - Potential 5% CTR improvement",
        "estimatedFixTime": "4 hours",
        "fixPriority": 3,
        "recommendation": "Audit and enhance titles/descriptions with secondary keywords",
        "implementationComplexity": "low"
      },
      {
        "id": "DESCRIPTION_LENGTH",
        "title": "Description Length Inconsistency",
        "severity": "minor",
        "affectedPercentage": "40%",
        "currentRange": "120-165 characters",
        "optimalRange": "155-160 characters",
        "impact": "LOW - Unused real estate and truncation risk",
        "estimatedFixTime": "2 hours",
        "fixPriority": 4,
        "recommendation": "Standardize descriptions to 155-160 character range",
        "implementationComplexity": "low"
      },
      {
        "id": "LIMITED_ALT_TEXT",
        "title": "Limited Alt Text on Images",
        "severity": "minor",
        "detected": 9,
        "affectedCount": 20,
        "coverage": "31%",
        "impact": "LOW-MEDIUM - Lost image search traffic, accessibility issues",
        "estimatedTrafficLoss": "2-5%",
        "estimatedFixTime": "4 hours",
        "fixPriority": 3,
        "recommendation": "Add meaningful alt text to all images systematically",
        "implementationComplexity": "low"
      },
      {
        "id": "NO_FAQPAGE_SCHEMA",
        "title": "No FAQPage Schema",
        "severity": "minor",
        "affectedPages": ["/about", "/contact", "/dmca"],
        "impact": "LOW - Missing rich snippets opportunity",
        "estimatedTrafficGain": "1-3%",
        "estimatedFixTime": "6 hours",
        "fixPriority": 4,
        "recommendation": "Create FAQ sections with FAQPage structured data",
        "implementationComplexity": "low"
      },
      {
        "id": "NO_BREADCRUMB_NAVIGATION",
        "title": "No Breadcrumb Navigation",
        "severity": "minor",
        "missingFrom": "Hierarchical pages",
        "schemaExists": true,
        "uiExists": false,
        "impact": "LOW - Better UX and internal linking signals",
        "estimatedFixTime": "4 hours",
        "fixPriority": 4,
        "recommendation": "Implement breadcrumb component on dynamic pages",
        "implementationComplexity": "low"
      }
    ],
    "metadataQualityAnalysis": {
      "titleTags": {
        "status": "GOOD",
        "coverage": "100%",
        "analysis": {
          "length": {
            "status": "✅ Good",
            "range": "45-65 characters",
            "notes": "Most titles optimal"
          },
          "keywordInclusion": {
            "status": "✅ Good",
            "coverage": "95%",
            "notes": "Primary keywords present on 27/28 pages"
          },
          "brandInclusion": {
            "status": "✅ Good",
            "coverage": "100%",
            "notes": "'Mangulina' on all pages"
          },
          "uniqueness": {
            "status": "✅ Good",
            "coverage": "100%",
            "notes": "28 unique titles across site"
          }
        }
      },
      "metaDescriptions": {
        "status": "MIXED",
        "coverage": "96%",
        "analysis": {
          "length": {
            "status": "⚠️ Mixed",
            "range": "120-165 characters",
            "optimalRange": "155-160 characters",
            "notes": "40% outside optimal range"
          },
          "keywordInclusion": {
            "status": "✅ Good",
            "coverage": "90%",
            "notes": "Most descriptions include target keywords"
          },
          "callToAction": {
            "status": "❌ Missing",
            "coverage": "0%",
            "notes": "No CTAs in meta descriptions"
          },
          "uniqueness": {
            "status": "✅ Good",
            "coverage": "96%",
            "notes": "27 unique descriptions"
          }
        }
      },
      "openGraphTags": {
        "status": "PARTIAL",
        "coverage": "96%",
        "breakdown": {
          "ogType": { "coverage": "100%", "status": "✅" },
          "ogTitle": { "coverage": "100%", "status": "✅" },
          "ogDescription": { "coverage": "100%", "status": "✅" },
          "ogImage": { "coverage": "21%", "status": "❌" },
          "ogUrl": { "coverage": "100%", "status": "✅" }
        },
        "imageGap": 22
      },
      "structuredData": {
        "status": "LIMITED",
        "coverage": "11%",
        "implemented": [
          "BreadcrumbList schema",
          "WebSite reference",
          "CollectionPage schema"
        ],
        "missing": [
          "Organization schema",
          "LocalBusiness schema",
          "Person schema",
          "MusicAlbum schema",
          "AudioObject schema",
          "FAQPage schema"
        ]
      }
    },
    "strengths": {
      "technical": {
        "robotsTxt": "✅ Proper conditional rules",
        "sitemap": "✅ Dynamic generation with prioritization",
        "canonicalUrls": "✅ All pages",
        "metadataBase": "✅ Configured",
        "noindexHandling": "✅ 404 pages marked"
      },
      "onPage": {
        "h1Hierarchy": "✅ Consistent across all pages",
        "openGraphMetadata": "✅ 96% coverage",
        "twitterCards": "✅ Configured",
        "titleTemplates": "✅ Brand suffix applied",
        "languageTag": "✅ Proper lang attribute"
      },
      "content": {
        "titleGeneration": "✅ Semantic functions",
        "metadataConsistency": "✅ Helper functions ensure consistency",
        "semanticHtml": "✅ Proper structure",
        "responsiveDesign": "✅ Mobile-friendly"
      }
    },
    "recommendationsByPriority": {
      "priority1_critical_week1": {
        "estimatedTime": "17 minutes",
        "tasks": [
          {
            "task": "Add metadata to /search page",
            "time": "5 minutes",
            "complexity": "trivial",
            "impact": "HIGH"
          },
          {
            "task": "Update manifest.json with correct names",
            "time": "2 minutes",
            "complexity": "trivial",
            "impact": "HIGH"
          },
          {
            "task": "Add 5 new pages to sitemap.ts",
            "time": "10 minutes",
            "complexity": "trivial",
            "impact": "HIGH"
          }
        ]
      },
      "priority2_major_month1": {
        "estimatedTime": "14-16 hours",
        "tasks": [
          {
            "task": "Create 13 OG image templates",
            "time": "8 hours",
            "complexity": "moderate",
            "impact": "HIGH"
          },
          {
            "task": "Implement full structured data",
            "time": "6-8 hours",
            "complexity": "moderate",
            "impact": "MEDIUM-HIGH"
          }
        ]
      },
      "priority3_medium_quarter1": {
        "estimatedTime": "12 hours",
        "tasks": [
          {
            "task": "Keyword optimization audit",
            "time": "4 hours",
            "complexity": "low",
            "impact": "MEDIUM"
          },
          {
            "task": "Add alt text to images",
            "time": "4 hours",
            "complexity": "low",
            "impact": "MEDIUM"
          },
          {
            "task": "Create FAQ sections with schema",
            "time": "6-8 hours",
            "complexity": "moderate",
            "impact": "LOW-MEDIUM"
          }
        ]
      },
      "priority4_minor_quarter2": {
        "estimatedTime": "10 hours",
        "tasks": [
          {
            "task": "Description length standardization",
            "time": "2 hours",
            "complexity": "low"
          },
          {
            "task": "Breadcrumb component implementation",
            "time": "4 hours",
            "complexity": "low"
          },
          {
            "task": "Performance optimization",
            "time": "4-6 hours",
            "complexity": "moderate"
          }
        ]
      }
    },
    "expectedSeoImpact": {
      "quickWins_week1": {
        "timeframe": "1 week",
        "estimatedImpact": "+0.5-1.0% organic traffic",
        "details": "Search page indexing, new page discovery"
      },
      "mediumTerm_month1to2": {
        "timeframe": "1-2 months",
        "estimatedImpact": "+5-10% organic traffic",
        "details": "OG images improve social referral, structured data enables rich snippets"
      },
      "longTerm_quarter1to2": {
        "timeframe": "3-6 months",
        "estimatedImpact": "+15-25% organic traffic",
        "details": "Comprehensive schema.org, entity recognition, voice search"
      },
      "totalPotential": "+25-40% organic traffic increase over 6 months"
    },
    "competitiveAnalysis": {
      "comparisonPoints": [
        {
          "feature": "Basic Metadata",
          "mangulina": "✅",
          "competitors": "✅",
          "status": "Par"
        },
        {
          "feature": "Structured Data",
          "mangulina": "⚠️ Limited",
          "competitors": "✅ Comprehensive",
          "status": "Behind"
        },
        {
          "feature": "Social Cards",
          "mangulina": "⚠️ Partial",
          "competitors": "✅ Full",
          "status": "Behind"
        },
        {
          "feature": "Breadcrumbs",
          "mangulina": "❌",
          "competitors": "✅",
          "status": "Behind"
        },
        {
          "feature": "FAQ Schema",
          "mangulina": "❌",
          "competitors": "✅",
          "status": "Behind"
        }
      ],
      "opportunity": "Competitive advantage in Dominican music search through comprehensive schema.org implementation"
    },
    "successMetrics": {
      "monthlyTracking": [
        "Organic traffic growth %",
        "Keyword ranking improvements",
        "Rich snippet impressions",
        "Click-through rate (CTR) changes",
        "Search console coverage",
        "New/updated pages crawled"
      ],
      "tools": [
        "Google Search Console",
        "Google Analytics 4",
        "SEMrush / Ahrefs",
        "Lighthouse (Page Speed)"
      ]
    },
    "professionalConclusion": {
      "overallGrade": "B+",
      "gradeJustification": "Solid technical foundation with clear improvement opportunities",
      "timeline": "3-6 months to A- level with recommended implementations",
      "estimatedRoi": "25-40% organic traffic increase",
      "nextReview": "90 days"
    }
  }
}
