{
  "platform": "youtube",
  "lastCompletedOffset": 4000,
  "pageSize": 1000,
  "startedAt": "2026-06-17T03:27:41.967Z",
  "updatedAt": "2026-06-17T20:44:33.946Z",
  "totalInserted": 2162,
  "totalUpdated": 44,
  "totalPages": 5,
  "quotaDate": "2026-06-17",
  "quotaUsedToday": 1900,
  "quotaUsedByKeyToday": [
    95,
    95,
    95,
    95,
    95,
    95,
    95,
    95,
    95,
    95,
    95,
    95,
    95,
    95,
    95,
    95,
    95,
    95,
    95,
    95
  ],
  "currentKeyIndex": 9,
  "keyCount": 20
}